natricine_aws/__init__.py
natricine_aws/config.py
natricine_aws/marshaling.py
natricine_aws/sns.py
natricine_aws/sqs.py
natricine_aws-0.1.0.dist-info/WHEEL
natricine_aws-0.1.0.dist-info/METADATA
natricine_aws-0.1.0.dist-info/RECORD
