Metadata-Version: 2.3
Name: natricine-aws
Version: 0.1.0
Summary: AWS SNS/SQS backend for natricine
Requires-Dist: natricine
Requires-Dist: aioboto3>=13.0
Requires-Dist: pytest ; extra == 'test'
Requires-Dist: pytest-anyio ; extra == 'test'
Requires-Dist: testcontainers[localstack] ; extra == 'test'
Requires-Dist: natricine-conformance ; extra == 'test'
Requires-Dist: types-aiobotocore[sns,sqs] ; extra == 'types'
Requires-Python: >=3.11
Provides-Extra: test
Provides-Extra: types
